garbledave_package/__init__.py
garbledave_package/garbledave.py
garbledave_package-1.0.0.dist-info/METADATA
garbledave_package-1.0.0.dist-info/WHEEL
garbledave_package-1.0.0.dist-info/licenses/LICENSE
garbledave_package-1.0.0.dist-info/RECORD
