Metadata-Version: 2.1
Name: garbledave_package
Version: 1.0.0
Summary: simplified obfustication
Project-URL: Homepage, https://github.com/daveskura/garble
Project-URL: Author Linkedin, https://www.linkedin.com/in/2166883
Author-email: Dave Skura <dskura@gmail.com>
License-File: LICENSE
Classifier: License :: OSI Approved :: MIT License
Classifier: Operating System :: OS Independent
Classifier: Programming Language :: Python :: 3
Requires-Python: >=3.7
